molecule_vmware/__init__.py
molecule_vmware/driver.py
molecule_vmware/cookiecutter/cookiecutter.json
molecule_vmware/cookiecutter/{{cookiecutter.molecule_directory}}/{{cookiecutter.scenario_name}}/INSTALL.rst
molecule_vmware/cookiecutter/{{cookiecutter.molecule_directory}}/{{cookiecutter.scenario_name}}/converge.yml
molecule_vmware/cookiecutter/{{cookiecutter.molecule_directory}}/{{cookiecutter.scenario_name}}/create.yml
molecule_vmware/cookiecutter/{{cookiecutter.molecule_directory}}/{{cookiecutter.scenario_name}}/destroy.yml
molecule_vmware/cookiecutter/{{cookiecutter.molecule_directory}}/{{cookiecutter.scenario_name}}/molecule.yml
molecule_vmware/cookiecutter/{{cookiecutter.molecule_directory}}/{{cookiecutter.scenario_name}}/handlers/main.yml
molecule_vmware/cookiecutter/{{cookiecutter.molecule_directory}}/{{cookiecutter.scenario_name}}/tasks/create_linux_instance.yml
molecule_vmware/cookiecutter/{{cookiecutter.molecule_directory}}/{{cookiecutter.scenario_name}}/tasks/create_windows_instance.yml
molecule_vmware-0.3.6.dist-info/LICENSE
molecule_vmware-0.3.6.dist-info/METADATA
molecule_vmware-0.3.6.dist-info/WHEEL
molecule_vmware-0.3.6.dist-info/entry_points.txt
molecule_vmware-0.3.6.dist-info/top_level.txt
molecule_vmware-0.3.6.dist-info/RECORD
